adencoding/__init__.py
AdEncoding-2.dist-info/LICENSE
AdEncoding-2.dist-info/METADATA
AdEncoding-2.dist-info/WHEEL
AdEncoding-2.dist-info/top_level.txt
AdEncoding-2.dist-info/RECORD
