Metadata-Version: 2.1
Name: AdEncoding
Version: 2
Summary: The most advanced yet simplest encoding system!
Home-page: https://github.com/CraftYun83/AVEncoding
Author: CraftYun83
Author-email: craftyun83@gmail.com
License: UNKNOWN
Platform: UNKNOWN
Classifier: Programming Language :: Python :: 3
Classifier: License :: OSI Approved :: MIT License
Classifier: Operating System :: OS Independent
Requires-Python: >=3.6
